pywhatkit/__init__.py
pywhatkit/ascii_art.py
pywhatkit/handwriting.py
pywhatkit/mail.py
pywhatkit/misc.py
pywhatkit/py.typed
pywhatkit/remotekit.py
pywhatkit/sc.py
pywhatkit/whats.py
pywhatkit/core/__init__.py
pywhatkit/core/core.py
pywhatkit/core/exceptions.py
pywhatkit/core/log.py
pywhatkit-5.4.dist-info/LICENSE
pywhatkit-5.4.dist-info/METADATA
pywhatkit-5.4.dist-info/WHEEL
pywhatkit-5.4.dist-info/top_level.txt
pywhatkit-5.4.dist-info/RECORD
