Metadata-Version: 2.1
Name: pywhatkit
Version: 5.4
Summary: PyWhatKit is a Simple and Powerful WhatsApp Automation Library with many useful Features
Home-page: https://github.com/Ankit404butfound/PyWhatKit
Author: Ankit Raj Mahapatra
Author-email: ankitrajjitendra816@gmail.com
License: MIT
Download-URL: https://github.com/Ankit404butfound/PyWhatKit/archive/refs/tags/5.2.zip
Keywords: sendwhatmsg,info,playonyt,search,watch_tutorial
Platform: UNKNOWN
Classifier: Development Status :: 5 - Production/Stable
Classifier: Intended Audience :: Developers
Classifier: Topic :: Software Development :: Build Tools
Classifier: License :: OSI Approved :: MIT License
Classifier: Programming Language :: Python :: 3.8
Classifier: Programming Language :: Python :: 3.9
Classifier: Programming Language :: Python :: 3.10
License-File: LICENSE
